README.md
setup.py
installerapp/__init__.py
installerapp/app.py
installerapp/namehandler.py
installerapp.egg-info/PKG-INFO
installerapp.egg-info/SOURCES.txt
installerapp.egg-info/dependency_links.txt
installerapp.egg-info/requires.txt
installerapp.egg-info/top_level.txt