Metadata-Version: 2.1
Name: installerapp
Version: 0.9.3
Summary: Python module to build installer
Home-page: https://github.com/novus-alex/InstallerApp
Author: Alex
Author-email: alexandre@hachet.com
License: MIT
Download-URL: https://github.com/novus-alex/InstallerApp/archive/refs/tags/0.2.tar.gz
Keywords: INSTALLER
Platform: UNKNOWN
Classifier: Development Status :: 3 - Alpha
Classifier: Intended Audience :: Developers
Classifier: Topic :: Software Development :: Build Tools
Classifier: License :: OSI Approved :: MIT License
Classifier: Programming Language :: Python :: 3
Classifier: Programming Language :: Python :: 3.9
